isfree-1.0.0.dist-info/licenses/LICENSE
isfree-1.0.0.dist-info/licenses/LICENSE.txt
package/__init__.py
package/cli.py
package/main.py
isfree-1.0.0.dist-info/METADATA
isfree-1.0.0.dist-info/WHEEL
isfree-1.0.0.dist-info/entry_points.txt
isfree-1.0.0.dist-info/top_level.txt
isfree-1.0.0.dist-info/RECORD
