Metadata-Version: 2.4
Name: isfree
Version: 1.0.0
Summary: Check if a domain is available using DNS
Author-email: Rocktim Saikia <rocktimthedev@gmail.com>
License: MIT License
Project-URL: homepage, https://github.com/rocktimsaikia/package
Project-URL: repository, https://github.com/rocktimsaikia/package
Project-URL: issues, https://github.com/rocktimsaikia/package/issues
Keywords: domain,dns,availability,cli
Classifier: Development Status :: 3 - Alpha
Classifier: Intended Audience :: Developers
Classifier: License :: OSI Approved :: MIT License
Classifier: Programming Language :: Python :: 3
Classifier: Programming Language :: Python :: 3.8
Classifier: Programming Language :: Python :: 3.9
Requires-Python: >=3.8
License-File: LICENSE
License-File: LICENSE.txt
Requires-Dist: dnspython>=2.0.0
Provides-Extra: dev
Requires-Dist: pre-commit; extra == "dev"
Dynamic: license-file
